satoi/__init__.py
satoi/deployment_tool.py
satoi-0.0.1.dist-info/LICENSE
satoi-0.0.1.dist-info/METADATA
satoi-0.0.1.dist-info/WHEEL
satoi-0.0.1.dist-info/top_level.txt
satoi-0.0.1.dist-info/RECORD
