Metadata-Version: 2.1
Name: satoi
Version: 0.0.1
Summary: A small deployment automation package
Author-email: Mykyta Nechepurenko <mykytanechepurenko@gmail.com>
Classifier: Programming Language :: Python :: 3
Classifier: License :: OSI Approved :: MIT License
Classifier: Operating System :: OS Independent
Requires-Python: >=3.8
License-File: LICENSE
